dbf2csv/__init__.py
dbf2csv/__main__.py
dbf2csv/dbfreader.py
dbf2csv/dbfsignature.py
dbf2csv_dbase7-0.6.5.dist-info/METADATA
dbf2csv_dbase7-0.6.5.dist-info/WHEEL
dbf2csv_dbase7-0.6.5.dist-info/entry_points.txt
dbf2csv_dbase7-0.6.5.dist-info/RECORD
